audiosetmanager/AudioSet.py
audiosetmanager/__init__.py
audiosetmanager/__main__.py
audiosetmanager/constants.py
audiosetmanager/AudioSet Data/balanced_train_segments.txt
audiosetmanager/AudioSet Data/class_labels_indices.txt
tests/__init__.py
audioset_manager-0.0.8.dist-info/METADATA
audioset_manager-0.0.8.dist-info/WHEEL
audioset_manager-0.0.8.dist-info/top_level.txt
audioset_manager-0.0.8.dist-info/RECORD
