Metadata-Version: 2.1
Name: audioset-manager
Version: 0.0.8
Summary: A simple python package for managing the audio data from Google Research's ontology of 632 audio event classes.
Home-page: https://github.com/gitUmaru/AudioSet-Data-Manager
Author: Muhammad Umar Ali
Author-email: umaruali@student.ubc.ca
Classifier: Programming Language :: Python :: 3
Classifier: Operating System :: OS Independent
Requires-Dist: pydub
Requires-Dist: youtube-dl
Requires-Dist: pandas
